odoo/addons/web_widget_remote_measure/README.rst
odoo/addons/web_widget_remote_measure/__init__.py
odoo/addons/web_widget_remote_measure/__manifest__.py
odoo/addons/web_widget_remote_measure/controllers/__init__.py
odoo/addons/web_widget_remote_measure/controllers/main.py
odoo/addons/web_widget_remote_measure/i18n/es.po
odoo/addons/web_widget_remote_measure/i18n/it.po
odoo/addons/web_widget_remote_measure/i18n/web_widget_remote_measure.pot
odoo/addons/web_widget_remote_measure/models/__init__.py
odoo/addons/web_widget_remote_measure/models/remote_measure_device.py
odoo/addons/web_widget_remote_measure/models/res_users.py
odoo/addons/web_widget_remote_measure/models/res_users_settings.py
odoo/addons/web_widget_remote_measure/readme/CONFIGURE.md
odoo/addons/web_widget_remote_measure/readme/CONTRIBUTORS.md
odoo/addons/web_widget_remote_measure/readme/DESCRIPTION.md
odoo/addons/web_widget_remote_measure/readme/ROADMAP.md
odoo/addons/web_widget_remote_measure/readme/USAGE.md
odoo/addons/web_widget_remote_measure/security/ir.model.access.csv
odoo/addons/web_widget_remote_measure/security/security.xml
odoo/addons/web_widget_remote_measure/static/description/icon.png
odoo/addons/web_widget_remote_measure/static/description/index.html
odoo/addons/web_widget_remote_measure/static/src/remote_measure_field/remote_measure_field.esm.js
odoo/addons/web_widget_remote_measure/static/src/remote_measure_field/remote_measure_field.scss
odoo/addons/web_widget_remote_measure/static/src/remote_measure_field/remote_measure_field.xml
odoo/addons/web_widget_remote_measure/static/src/systray/systray_device_selector.esm.js
odoo/addons/web_widget_remote_measure/static/src/systray/systray_device_selector.scss
odoo/addons/web_widget_remote_measure/static/src/systray/systray_device_selector.xml
odoo/addons/web_widget_remote_measure/views/remote_measure_device_views.xml
odoo/addons/web_widget_remote_measure/views/res_users_views.xml
odoo_addon_web_widget_remote_measure-17.0.1.0.1.1.dist-info/METADATA
odoo_addon_web_widget_remote_measure-17.0.1.0.1.1.dist-info/WHEEL
odoo_addon_web_widget_remote_measure-17.0.1.0.1.1.dist-info/top_level.txt
odoo_addon_web_widget_remote_measure-17.0.1.0.1.1.dist-info/RECORD
